foodemoji/__init__.py
foodemoji/foodemojis.json
german_foodemoji-1.1.11.dist-info/LICENSE
german_foodemoji-1.1.11.dist-info/METADATA
german_foodemoji-1.1.11.dist-info/WHEEL
german_foodemoji-1.1.11.dist-info/top_level.txt
german_foodemoji-1.1.11.dist-info/zip-safe
german_foodemoji-1.1.11.dist-info/RECORD
