Metadata-Version: 2.1
Name: german-foodemoji
Version: 1.1.11
Summary: Decorate German text with food specific emojis
Author-email: cuzi <cuzi@openmail.cc>
License: MIT
Project-URL: Homepage, https://github.com/cvzi/foodemoji
Project-URL: Documentation, https://foodemoji.readthedocs.io/
Project-URL: Downloads, https://pypi.org/project/german-foodemoji/
Classifier: Programming Language :: Python
Classifier: Programming Language :: Python :: 3.7
Classifier: Programming Language :: Python :: 3.8
Classifier: Programming Language :: Python :: 3.9
Classifier: Programming Language :: Python :: 3.10
Classifier: Programming Language :: Python :: 3.11
Classifier: License :: OSI Approved :: MIT License
Classifier: Operating System :: OS Independent
Classifier: Topic :: Internet :: WWW/HTTP :: Dynamic Content
Classifier: Topic :: Communications :: Chat
Classifier: Topic :: Printing
Classifier: Topic :: Text Processing :: General
License-File: LICENSE
Provides-Extra: testing
Requires-Dist: emoji ; extra == 'testing'
Requires-Dist: packaging ; extra == 'testing'
